oocone-0.6.5.dist-info/METADATA
oocone-0.6.5.dist-info/WHEEL
oocone-0.6.5.dist-info/entry_points.txt
oocone-0.6.5.dist-info/licenses/LICENSE
oocone/__init__.py
oocone/_internal/__init__.py
oocone/_internal/api_types.py
oocone/_internal/html_table.py
oocone/_internal/quirks.py
oocone/_internal/scrape_consumption.py
oocone/_internal/scrape_meter_table.py
oocone/_internal/scrape_photovoltaic.py
oocone/_internal/scrape_timeseries.py
oocone/_internal/scrape_traffic_light.py
oocone/auth.py
oocone/enocoo.py
oocone/errors.py
oocone/model.py
oocone/py.typed
oocone-0.6.5.dist-info/RECORD
