Metadata-Version: 2.1
Name: oocone
Version: 0.6.5
Summary: Unofficial library for interacting with an enocoo energy management system
Author-Email: Simon Leiner <simon@leiner.me>
License: ISC
Classifier: Development Status :: 3 - Alpha
Classifier: Programming Language :: Python :: 3
Project-URL: Repository, https://github.com/sleiner/oocone
Project-URL: Homepage, https://github.com/sleiner/oocone
Requires-Python: >=3.13.2
Requires-Dist: aiohttp>=3.13.2
Requires-Dist: beautifulsoup4>=4.13.3
